{
  "id": "20241121_161714",
  "strategy_name": "macd",
  "parameters": {},
  "results": {
    "returns": [
      {
        "time": "2024-10-01",
        "value": 0.0
      },
      {
        "time": "2024-10-02",
        "value": 0.0
      },
      {
        "time": "2024-10-03",
        "value": -0.004894677804091807
      },
      {
        "time": "2024-10-04",
        "value": -0.009877527975529543
      },
      {
        "time": "2024-10-07",
        "value": -0.032185848077265544
      },
      {
        "time": "2024-10-08",
        "value": -0.0499975733230138
      },
      {
        "time": "2024-10-09",
        "value": -0.06586109090609471
      },
      {
        "time": "2024-10-10",
        "value": -0.06789589803063756
      },
      {
        "time": "2024-10-11",
        "value": -0.07395960088212927
      },
      {
        "time": "2024-10-14",
        "value": -0.05869854744805847
      },
      {
        "time": "2024-10-15",
        "value": -0.04832104354602684
      },
      {
        "time": "2024-10-16",
        "value": -0.056745177367788946
      },
      {
        "time": "2024-10-17",
        "value": -0.05523940020260876
      },
      {
        "time": "2024-10-18",
        "value": -0.0436410244589881
      },
      {
        "time": "2024-10-21",
        "value": -0.03761797796395039
      },
      {
        "time": "2024-10-22",
        "value": -0.04014109652571918
      },
      {
        "time": "2024-10-23",
        "value": -0.06089616649546514
      },
      {
        "time": "2024-10-24",
        "value": -0.06166932109059953
      },
      {
        "time": "2024-10-25",
        "value": -0.05825089236728642
      },
      {
        "time": "2024-10-28",
        "value": -0.05015238239125197
      },
      {
        "time": "2024-10-29",
        "value": -0.049053603950390046
      },
      {
        "time": "2024-10-30",
        "value": -0.06358209698009776
      },
      {
        "time": "2024-10-31",
        "value": -0.04653042322293843
      },
      {
        "time": "2024-11-01",
        "value": -0.03386870066162628
      },
      {
        "time": "2024-11-04",
        "value": -0.029967913864613616
      },
      {
        "time": "2024-11-05",
        "value": -0.03625972223024443
      },
      {
        "time": "2024-11-06",
        "value": -0.03311127702054728
      },
      {
        "time": "2024-11-07",
        "value": -0.05377570981635582
      },
      {
        "time": "2024-11-08",
        "value": -0.05265142971415748
      },
      {
        "time": "2024-11-11",
        "value": -0.041256153329524814
      },
      {
        "time": "2024-11-12",
        "value": -0.041256153329524814
      },
      {
        "time": "2024-11-13",
        "value": -0.045061538222823105
      },
      {
        "time": "2024-11-14",
        "value": -0.05821148102754847
      },
      {
        "time": "2024-11-15",
        "value": -0.044923600191009605
      },
      {
        "time": "2024-11-18",
        "value": -0.0577428660041196
      },
      {
        "time": "2024-11-19",
        "value": -0.05666847922104967
      },
      {
        "time": "2024-11-20",
        "value": -0.05369318637839793
      }
    ],
    "drawdown": [
      {
        "time": "2024-10-01",
        "value": 0.0
      },
      {
        "time": "2024-10-02",
        "value": 0.0
      },
      {
        "time": "2024-10-03",
        "value": -0.004894677804091807
      },
      {
        "time": "2024-10-04",
        "value": -0.009877527975529543
      },
      {
        "time": "2024-10-07",
        "value": -0.032185848077265544
      },
      {
        "time": "2024-10-08",
        "value": -0.0499975733230138
      },
      {
        "time": "2024-10-09",
        "value": -0.06586109090609471
      },
      {
        "time": "2024-10-10",
        "value": -0.06789589803063756
      },
      {
        "time": "2024-10-11",
        "value": -0.07395960088212927
      },
      {
        "time": "2024-10-14",
        "value": -0.05869854744805847
      },
      {
        "time": "2024-10-15",
        "value": -0.04832104354602684
      },
      {
        "time": "2024-10-16",
        "value": -0.056745177367788946
      },
      {
        "time": "2024-10-17",
        "value": -0.05523940020260876
      },
      {
        "time": "2024-10-18",
        "value": -0.0436410244589881
      },
      {
        "time": "2024-10-21",
        "value": -0.03761797796395039
      },
      {
        "time": "2024-10-22",
        "value": -0.04014109652571918
      },
      {
        "time": "2024-10-23",
        "value": -0.06089616649546514
      },
      {
        "time": "2024-10-24",
        "value": -0.06166932109059953
      },
      {
        "time": "2024-10-25",
        "value": -0.05825089236728642
      },
      {
        "time": "2024-10-28",
        "value": -0.05015238239125197
      },
      {
        "time": "2024-10-29",
        "value": -0.049053603950390046
      },
      {
        "time": "2024-10-30",
        "value": -0.06358209698009776
      },
      {
        "time": "2024-10-31",
        "value": -0.04653042322293843
      },
      {
        "time": "2024-11-01",
        "value": -0.03386870066162628
      },
      {
        "time": "2024-11-04",
        "value": -0.029967913864613616
      },
      {
        "time": "2024-11-05",
        "value": -0.03625972223024443
      },
      {
        "time": "2024-11-06",
        "value": -0.03311127702054728
      },
      {
        "time": "2024-11-07",
        "value": -0.05377570981635582
      },
      {
        "time": "2024-11-08",
        "value": -0.05265142971415748
      },
      {
        "time": "2024-11-11",
        "value": -0.041256153329524814
      },
      {
        "time": "2024-11-12",
        "value": -0.041256153329524814
      },
      {
        "time": "2024-11-13",
        "value": -0.045061538222823105
      },
      {
        "time": "2024-11-14",
        "value": -0.05821148102754847
      },
      {
        "time": "2024-11-15",
        "value": -0.044923600191009605
      },
      {
        "time": "2024-11-18",
        "value": -0.0577428660041196
      },
      {
        "time": "2024-11-19",
        "value": -0.05666847922104967
      },
      {
        "time": "2024-11-20",
        "value": -0.05369318637839793
      }
    ],
    "total_return": -0.06419318637839792,
    "annual_return": -0.3133138903275844,
    "sharpe_ratio": -2.173077258891487,
    "max_drawdown": -0.07395960088212927,
    "win_rate": 0.5
  },
  "created_at": "2024-11-21T16:17:14.540112"
}